mediapipe_helper/__init__.py
mediapipe_helper/config.py
mediapipe_helper/face_landmark_helper.py
mediapipe_helper-0.0.5.dist-info/LICENSE.txt
mediapipe_helper-0.0.5.dist-info/METADATA
mediapipe_helper-0.0.5.dist-info/WHEEL
mediapipe_helper-0.0.5.dist-info/top_level.txt
mediapipe_helper-0.0.5.dist-info/RECORD
