Metadata-Version: 2.1
Name: mediapipe-helper
Version: 0.0.5
Summary: A package to help you utilise landmarks in the face_landmark feature of google open source mediapipe.
Home-page: https://github.com/LearningnRunning/py_face_landmark_helper
Author: learningnRunning
Author-email: max_sungrok@naver.com
Classifier: Development Status :: 5 - Production/Stable
Classifier: Intended Audience :: Education
Classifier: Intended Audience :: End Users/Desktop
Classifier: License :: OSI Approved :: Apache Software License
Classifier: Operating System :: POSIX
Classifier: Operating System :: Microsoft :: Windows
Classifier: Operating System :: MacOS :: MacOS X
Classifier: Topic :: Education
Classifier: Programming Language :: Python :: 3.6
Classifier: Programming Language :: Python :: 3.7
Classifier: Programming Language :: Python :: 3.8
Classifier: Programming Language :: Python :: 3.9
License-File: LICENSE.txt
Requires-Dist: mediapipe
Requires-Dist: opencv-python
Requires-Dist: pillow
